<Properties StartupConfiguration="{E94744D6-C8B0-AEC2-CE8A-D7A69BB1AE69}|">
  <MonoDevelop.Ide.Workbench ActiveDocument="Assets/Scripts/Model.cs">
    <Files>
      <File FileName="Assets/Scripts/ViewController.cs" Line="145" Column="52" />
      <File FileName="Assets/Scripts/Model.cs" Line="2508" Column="56" />
    </Files>
  </MonoDevelop.Ide.Workbench>
  <MonoDevelop.Ide.DebuggingService.PinnedWatches />
  <MonoDevelop.Ide.Workspace ActiveConfiguration="Debug" />
  <MonoDevelop.Ide.ItemProperties.Assembly-CSharp PreferredExecutionTarget="03be200a-96ea-4995-9678-65857cdccf2c" />
  <MonoDevelop.Ide.DebuggingService.Breakpoints>
    <BreakpointStore />
  </MonoDevelop.Ide.DebuggingService.Breakpoints>
  <MultiItemStartupConfigurations />
</Properties>